AutoItLibrary/Counter.py
AutoItLibrary/Logger.py
AutoItLibrary/__init__.py
RobotFramework/Extensions/AutoItLibrary/Au3Info.exe
RobotFramework/Extensions/AutoItLibrary/AutoItLibrary.html
RobotFramework/Extensions/AutoItLibrary/AutoItX.chm
RobotFramework/Extensions/AutoItLibrary/AutoItX3.dll
RobotFramework/Extensions/AutoItLibrary/AutoIt_License.html
RobotFramework/Extensions/AutoItLibrary/COPYRIGHT.txt
RobotFramework/Extensions/AutoItLibrary/LICENSE.txt
RobotFramework/Extensions/AutoItLibrary/tests/CalculatorGUIMap.py
RobotFramework/Extensions/AutoItLibrary/tests/Calculator_Test_Cases.html
RobotFramework/Extensions/AutoItLibrary/tests/RobotIDE.bat
RobotFramework/Extensions/AutoItLibrary/tests/RunTests.bat
RobotFramework/Extensions/AutoItLibrary/tests/__init__.html
robotframework_autoitlibrary-1.2.9.dist-info/LICENSE.txt
robotframework_autoitlibrary-1.2.9.dist-info/METADATA
robotframework_autoitlibrary-1.2.9.dist-info/WHEEL
robotframework_autoitlibrary-1.2.9.dist-info/top_level.txt
robotframework_autoitlibrary-1.2.9.dist-info/RECORD
