Metadata-Version: 2.1
Name: robotframework-autoitlibrary
Version: 1.2.9
Summary: AutoItLibrary for Robot Framework
Home-page: https://github.com/nokia/robotframework-autoitlibrary
Author: Joe Hisaishi
Author-email: joehisaishi1943@gmail.com
License: Apache License 2.0
Platform: Microsoft Windows
Classifier: Development Status :: 5 - Production/Stable
Classifier: License :: OSI Approved :: Apache Software License
Classifier: Operating System :: Microsoft :: Windows
Classifier: Programming Language :: Python
Classifier: Topic :: Software Development :: Testing
License-File: LICENSE.txt
Requires-Dist: robotframework
Requires-Dist: pywin32
Requires-Dist: pillow
